rtl/controller.v
module controller
(
    input clk,
    input rst,

    input start,
    input feed_done,

    output reg load,
    output reg shift_enable,
    output reg enable,
    output reg store_enable,
    output reg done
);

    //--------------------------------------------------
    // State Encoding
    //--------------------------------------------------

    localparam IDLE  = 3'd0;
    localparam LOAD  = 3'd1;
    localparam FEED  = 3'd2;
    localparam FLUSH = 3'd3;
    localparam STORE = 3'd4;
    localparam DONE  = 3'd5;

    reg [2:0] state;
    reg [2:0] next_state;

    reg [2:0] flush_count;

    //--------------------------------------------------
    // State Register
    //--------------------------------------------------

    always @(posedge clk) begin

        if (rst)
            state <= IDLE;
        else
            state <= next_state;

    end

    //--------------------------------------------------
    // Flush Counter
    //--------------------------------------------------

    always @(posedge clk) begin

        if (rst)
            flush_count <= 3'd0;

        else if (state != FLUSH)
            flush_count <= 3'd0;

        else if (flush_count < 3'd6)
            flush_count <= flush_count + 1'b1;

    end

    //--------------------------------------------------
    // Next State Logic
    //--------------------------------------------------

    always @(*) begin

        next_state = state;

        case (state)

            IDLE:
            begin
                if (start)
                    next_state = LOAD;
            end

            LOAD:
            begin
                next_state = FEED;
            end

            FEED:
            begin
                if (feed_done)
                    next_state = FLUSH;
            end

            FLUSH:
            begin
                if (flush_count == 3'd6)
                    next_state = STORE;
            end

            STORE:
            begin
                next_state = DONE;
            end

            DONE:
            begin
                if (!start)
                    next_state = IDLE;
            end

            default:
            begin
                next_state = IDLE;
            end

        endcase

    end

    //--------------------------------------------------
    // Output Logic
    //--------------------------------------------------

    always @(*) begin

        // Default outputs

        load         = 1'b0;
        shift_enable = 1'b0;
        enable       = 1'b0;
        store_enable = 1'b0;
        done         = 1'b0;

        case (state)

            IDLE:
            begin
            end

            LOAD:
            begin
                load = 1'b1;
            end

            FEED:
            begin
                shift_enable = 1'b1;
                enable = 1'b1;
            end

            FLUSH:
            begin
                enable = 1'b1;
            end

            STORE:
            begin
                store_enable = 1'b1;
            end

            DONE:
            begin
                done = 1'b1;
            end

            default:
            begin
            end

        endcase

    end

endmodule

tb/controller_tb.v
`timescale 1ns / 1ps

module controller_tb;

//--------------------------------------------------
// Inputs
//--------------------------------------------------

reg clk;
reg rst;

reg start;
reg feed_done;

//--------------------------------------------------
// Outputs
//--------------------------------------------------

wire load;
wire shift_enable;
wire enable;
wire store_enable;
wire done;

//--------------------------------------------------
// DUT
//--------------------------------------------------

controller uut
(
    .clk(clk),
    .rst(rst),

    .start(start),
    .feed_done(feed_done),

    .load(load),
    .shift_enable(shift_enable),
    .enable(enable),
    .store_enable(store_enable),
    .done(done)
);

//--------------------------------------------------
// Clock
//--------------------------------------------------

always #5 clk = ~clk;

//--------------------------------------------------
// Test
//--------------------------------------------------

initial
begin

    $dumpfile("controller_tb.vcd");
    $dumpvars(0, controller_tb);

    clk = 0;
    rst = 1;

    start = 0;
    feed_done = 0;

    //----------------------------
    // Reset
    //----------------------------

    #20;
    rst = 0;

    //----------------------------
    // Start controller
    //----------------------------

    #10;
    start = 1;

    //----------------------------
    // Stay in FEED
    //----------------------------

    repeat(8)
        @(posedge clk);

    //----------------------------
    // Input buffer finished
    //----------------------------

    feed_done = 1;

    @(posedge clk);

    feed_done = 0;

    //----------------------------
    // Wait for FLUSH + STORE
    //----------------------------

    repeat(10)
        @(posedge clk);

    //----------------------------
    // Return to IDLE
    //----------------------------

    start = 0;

    repeat(3)
        @(posedge clk);

    $finish;

end;

//--------------------------------------------------
// Console Output
//--------------------------------------------------

initial
begin

    $display("--------------------------------------------------------------------------------------");
    $display("Time\tState\tFlush\tLoad\tShift\tEnable\tStore\tDone");
    $display("--------------------------------------------------------------------------------------");

    $monitor("%0t\t%0d\t%0d\t%b\t%b\t%b\t%b\t%b",
        $time,
        uut.state,
        uut.flush_count,
        load,
        shift_enable,
        enable,
        store_enable,
        done
    );

end

endmodule

controller_tb.vcd
$date
	Fri Jul 31 23:31:28 2026
$end
$version
	Icarus Verilog
$end
$timescale
	1ps
$end
$scope module controller_tb $end
$var wire 1 ! store_enable $end
$var wire 1 " shift_enable $end
$var wire 1 # load $end
$var wire 1 $ enable $end
$var wire 1 % done $end
$var reg 1 & clk $end
$var reg 1 ' feed_done $end
$var reg 1 ( rst $end
$var reg 1 ) start $end
$scope module uut $end
$var wire 1 & clk $end
$var wire 1 ' feed_done $end
$var wire 1 ( rst $end
$var wire 1 ) start $end
$var parameter 3 * DONE $end
$var parameter 3 + FEED $end
$var parameter 3 , FLUSH $end
$var parameter 3 - IDLE $end
$var parameter 3 . LOAD $end
$var parameter 3 / STORE $end
$var reg 1 % done $end
$var reg 1 $ enable $end
$var reg 3 0 flush_count [2:0] $end
$var reg 1 # load $end
$var reg 3 1 next_state [2:0] $end
$var reg 1 " shift_enable $end
$var reg 3 2 state [2:0] $end
$var reg 1 ! store_enable $end
$upscope $end
$upscope $end
$enddefinitions $end
$comment Show the parameter values. $end
$dumpall
b100 /
b1 .
b0 -
b11 ,
b10 +
b101 *
$end
#0
$dumpvars
bx 2
b0 1
bx 0
0)
1(
0'
0&
x%
x$
x#
x"
x!
$end
#5000
0%
0!
0$
0"
0#
b0 2
b0 0
1&
#10000
0&
#15000
1&
#20000
0&
0(
#25000
1&
#30000
b1 1
0&
1)
#35000
1#
b10 1
b1 2
1&
#40000
0&
#45000
1$
1"
0#
b10 2
1&
#50000
0&
#55000
1&
#60000
0&
#65000
1&
#70000
0&
#75000
1&
#80000
0&
#85000
1&
#90000
0&
#95000
1&
#100000
0&
#105000
b11 1
1'
1&
#110000
0&
#115000
1$
0"
b11 2
b11 1
0'
1&
#120000
0&
#125000
b1 0
1&
#130000
0&
#135000
b10 0
1&
#140000
0&
#145000
b11 0
1&
#150000
0&
#155000
b100 0
1&
#160000
0&
#165000
b101 0
1&
#170000
0&
#175000
b100 1
b110 0
1&
#180000
0&
#185000
1!
0$
b101 1
b100 2
1&
#190000
0&
#195000
1%
0!
b0 0
b101 2
1&
#200000
0&
#205000
1&
#210000
0&
#215000
b0 1
0)
1&
#220000
0&
#225000
0%
b0 2
1&
