rtl/input_buffer.v
module input_buffer
#(
    parameter DATA_WIDTH = 8
)
(
    input clk,
    input rst,

    // Load matrices
    input load,
    input signed [16*DATA_WIDTH-1:0] A_flat_in,
    input signed [16*DATA_WIDTH-1:0] B_flat_in,

    // Shifts data after every clock cycle
    input shift_enable,

    // Outputs to left edge of array
    output reg signed [DATA_WIDTH-1:0] A0,
    output reg signed [DATA_WIDTH-1:0] A1,
    output reg signed [DATA_WIDTH-1:0] A2,
    output reg signed [DATA_WIDTH-1:0] A3,

    // Outputs to top edge of array
    output reg signed [DATA_WIDTH-1:0] B0,
    output reg signed [DATA_WIDTH-1:0] B1,
    output reg signed [DATA_WIDTH-1:0] B2,
    output reg signed [DATA_WIDTH-1:0] B3,

    // High once all real inputs have been injected
    output reg feed_done
);

    // Matrix storage
    reg signed [DATA_WIDTH-1:0] A_mem [0:15];
    reg signed [DATA_WIDTH-1:0] B_mem [0:15];

    // Injection cycle
    reg [3:0] cycle;

    integer i;

    // Load matrices
    always @(posedge clk) begin
        if (rst) begin
            cycle <= 4'd0;
            for(i=0; i<16; i=i+1) begin
                A_mem[i] <= 0;
                B_mem[i] <= 0;
            end
        end
        else begin
            if(load) begin
                cycle <= 4'd0;
                for(i=0; i<16; i=i+1) begin
                    A_mem[i] <= A_flat_in[i*DATA_WIDTH +: DATA_WIDTH];
                    B_mem[i] <= B_flat_in[i*DATA_WIDTH +: DATA_WIDTH];
                end
            end
            else if(shift_enable) begin
                // Saturate cycle at 7 to prevent wraparound re-injection
                if (cycle < 4'd7) begin
                    cycle <= cycle + 1'b1;
                end
            end
        end
    end

    // Scheduler
    always @(*) begin
        // Default outputs are zero
        A0 = 0; A1 = 0; A2 = 0; A3 = 0;
        B0 = 0; B1 = 0; B2 = 0; B3 = 0;

        // All real data injected after cycle 6
        feed_done = (cycle >= 4'd6);

        case(cycle)
            4'd0: begin
                A0 = A_mem[0];
                B0 = B_mem[0];
            end

            4'd1: begin
                A0 = A_mem[1]; A1 = A_mem[4];
                B0 = B_mem[4]; B1 = B_mem[1];
            end

            4'd2: begin
                A0 = A_mem[2]; A1 = A_mem[5]; A2 = A_mem[8];
                B0 = B_mem[8]; B1 = B_mem[5]; B2 = B_mem[2];
            end

            4'd3: begin
                A0 = A_mem[3];  A1 = A_mem[6];  A2 = A_mem[9];  A3 = A_mem[12];
                B0 = B_mem[12]; B1 = B_mem[9];  B2 = B_mem[6];  B3 = B_mem[3];
            end

            4'd4: begin
                A1 = A_mem[7];  A2 = A_mem[10]; A3 = A_mem[13];
                B1 = B_mem[13]; B2 = B_mem[10]; B3 = B_mem[7];
            end

            4'd5: begin
                A2 = A_mem[11]; A3 = A_mem[14];
                B2 = B_mem[14]; B3 = B_mem[11];
            end

            4'd6: begin
                A3 = A_mem[15];
                B3 = B_mem[15];
            end

            default: begin
                // Zero padding after cycle 6
            end
        endcase
    end

endmodule

tb/input_buffer_tb.v
`timescale 1ns / 1ps

module input_buffer_tb;

parameter DATA_WIDTH = 8;

// Inputs
reg clk;
reg rst;
reg load;
reg shift_enable;
reg signed [16*DATA_WIDTH-1:0] A_flat_in;
reg signed [16*DATA_WIDTH-1:0] B_flat_in;

// Outputs
wire signed [DATA_WIDTH-1:0] A0;
wire signed [DATA_WIDTH-1:0] A1;
wire signed [DATA_WIDTH-1:0] A2;
wire signed [DATA_WIDTH-1:0] A3;

wire signed [DATA_WIDTH-1:0] B0;
wire signed [DATA_WIDTH-1:0] B1;
wire signed [DATA_WIDTH-1:0] B2;
wire signed [DATA_WIDTH-1:0] B3;

wire feed_done;


//--------------------------------------------------
// DUT
//--------------------------------------------------

input_buffer uut
(
    .clk(clk),
    .rst(rst),

    .load(load),
    .A_flat_in(A_flat_in),
    .B_flat_in(B_flat_in),

    .shift_enable(shift_enable),

    .A0(A0),
    .A1(A1),
    .A2(A2),
    .A3(A3),

    .B0(B0),
    .B1(B1),
    .B2(B2),
    .B3(B3),

    .feed_done(feed_done)
);


//--------------------------------------------------
// Clock (10 ns period)
//--------------------------------------------------

always #5 clk = ~clk;


//--------------------------------------------------
// Test
//--------------------------------------------------

initial
begin

    // Create waveform
    $dumpfile("input_buffer_tb.vcd");
    $dumpvars(0, input_buffer_tb);

    // Initialize
    clk = 0;
    rst = 1;
    load = 0;
    shift_enable = 0;

    A_flat_in = 0;
    B_flat_in = 0;

    //--------------------------------------------------
    // Matrix A
    //
    //  1  2  3  4
    //  5  6  7  8
    //  9 10 11 12
    // 13 14 15 16
    //--------------------------------------------------

    A_flat_in = {
        8'd16,8'd15,8'd14,8'd13,
        8'd12,8'd11,8'd10,8'd9,
        8'd8,8'd7,8'd6,8'd5,
        8'd4,8'd3,8'd2,8'd1
    };

    //--------------------------------------------------
    // Matrix B
    //
    //17 18 19 20
    //21 22 23 24
    //25 26 27 28
    //29 30 31 32
    //--------------------------------------------------

    B_flat_in = {
        8'd32,8'd31,8'd30,8'd29,
        8'd28,8'd27,8'd26,8'd25,
        8'd24,8'd23,8'd22,8'd21,
        8'd20,8'd19,8'd18,8'd17
    };

    // Hold reset
    #20;

    rst = 0;

    // Load matrices
    #10;
    load = 1;

    #10;
    load = 0;

    // Start shifting
    shift_enable = 1;

    // Run long enough to flush array
    #150;

    shift_enable = 0;

    #20;

    $finish;

end


//--------------------------------------------------
// Console Output
//--------------------------------------------------

initial
begin

    $display("--------------------------------------------------------------------------");
    $display("Time\tCycle\tA0 A1 A2 A3\t|\tB0 B1 B2 B3\t|\tfeed_done");
    $display("--------------------------------------------------------------------------");

    $monitor("%0t\t%0d\t%0d %0d %0d %0d\t|\t%0d %0d %0d %0d\t|\t%b",
             $time,
             uut.cycle,
             A0,A1,A2,A3,
             B0,B1,B2,B3,
             feed_done);

end

endmodule

input_buffer_tb.vcd
$date
	Wed Jul 29 20:29:58 2026
$end
$version
	Icarus Verilog
$end
$timescale
	1ps
$end
$scope module input_buffer_tb $end
$var wire 1 ! feed_done $end
$var wire 8 " B3 [7:0] $end
$var wire 8 # B2 [7:0] $end
$var wire 8 $ B1 [7:0] $end
$var wire 8 % B0 [7:0] $end
$var wire 8 & A3 [7:0] $end
$var wire 8 ' A2 [7:0] $end
$var wire 8 ( A1 [7:0] $end
$var wire 8 ) A0 [7:0] $end
$var parameter 32 * DATA_WIDTH $end
$var reg 128 + A_flat_in [127:0] $end
$var reg 128 , B_flat_in [127:0] $end
$var reg 1 - clk $end
$var reg 1 . load $end
$var reg 1 / rst $end
$var reg 1 0 shift_enable $end
$scope module uut $end
$var wire 128 1 A_flat_in [127:0] $end
$var wire 128 2 B_flat_in [127:0] $end
$var wire 1 - clk $end
$var wire 1 . load $end
$var wire 1 / rst $end
$var wire 1 0 shift_enable $end
$var parameter 32 3 DATA_WIDTH $end
$var reg 8 4 A0 [7:0] $end
$var reg 8 5 A1 [7:0] $end
$var reg 8 6 A2 [7:0] $end
$var reg 8 7 A3 [7:0] $end
$var reg 8 8 B0 [7:0] $end
$var reg 8 9 B1 [7:0] $end
$var reg 8 : B2 [7:0] $end
$var reg 8 ; B3 [7:0] $end
$var reg 4 < cycle [3:0] $end
$var reg 1 ! feed_done $end
$var integer 32 = i [31:0] $end
$upscope $end
$upscope $end
$enddefinitions $end
$comment Show the parameter values. $end
$dumpall
b1000 3
b1000 *
$end
#0
$dumpvars
bx =
bx <
bx ;
bx :
bx 9
bx 8
bx 7
bx 6
bx 5
bx 4
b100000000111110001111000011101000111000001101100011010000110010001100000010111000101100001010100010100000100110001001000010001 2
b10000000011110000111000001101000011000000101100001010000010010000100000000111000001100000010100000100000000110000001000000001 1
00
1/
0.
0-
b100000000111110001111000011101000111000001101100011010000110010001100000010111000101100001010100010100000100110001001000010001 ,
b10000000011110000111000001101000011000000101100001010000010010000100000000111000001100000010100000100000000110000001000000001 +
bx )
bx (
bx '
bx &
bx %
bx $
bx #
bx "
x!
$end
#5000
0!
b0 "
b0 ;
b0 #
b0 :
b0 $
b0 9
b0 %
b0 8
b0 &
b0 7
b0 '
b0 6
b0 (
b0 5
b0 )
b0 4
b0 <
b10000 =
1-
#10000
0-
#15000
b10000 =
1-
#20000
0-
0/
#25000
1-
#30000
0-
1.
#35000
b10001 %
b10001 8
b1 )
b1 4
b10000 =
1-
#40000
0-
10
0.
#45000
b10010 $
b10010 9
b101 (
b101 5
b10101 %
b10101 8
b10 )
b10 4
b1 <
1-
#50000
0-
#55000
b10011 #
b10011 :
b1001 '
b1001 6
b10110 $
b10110 9
b11001 %
b11001 8
b110 (
b110 5
b11 )
b11 4
b10 <
1-
#60000
0-
#65000
b10100 "
b10100 ;
b1101 &
b1101 7
b10111 #
b10111 :
b11010 $
b11010 9
b11101 %
b11101 8
b1010 '
b1010 6
b111 (
b111 5
b100 )
b100 4
b11 <
1-
#70000
0-
#75000
b11000 "
b11000 ;
b11011 #
b11011 :
b11110 $
b11110 9
b0 %
b0 8
b1110 &
b1110 7
b1011 '
b1011 6
b1000 (
b1000 5
b0 )
b0 4
b100 <
1-
#80000
0-
#85000
b11100 "
b11100 ;
b11111 #
b11111 :
b0 $
b0 9
b1111 &
b1111 7
b1100 '
b1100 6
b0 (
b0 5
b101 <
1-
#90000
0-
#95000
1!
b100000 "
b100000 ;
b0 #
b0 :
b10000 &
b10000 7
b0 '
b0 6
b110 <
1-
#100000
0-
#105000
b0 "
b0 ;
b0 &
b0 7
b111 <
1-
#110000
0-
#115000
b1000 <
1-
#120000
0-
#125000
b1001 <
1-
#130000
0-
#135000
b1010 <
1-
#140000
0-
#145000
b1011 <
1-
#150000
0-
#155000
b1100 <
1-
#160000
0-
#165000
b1101 <
1-
#170000
0-
#175000
b1110 <
1-
#180000
0-
#185000
b1111 <
1-
#190000
0-
00
