rtl/pe.v
module pe
#(
    parameter DATA_WIDTH = 8,
    parameter ACC_WIDTH  = 32
)
(
    input clk,
    input rst,
    input enable,

    input  signed [DATA_WIDTH-1:0] A_in,
    input  signed [DATA_WIDTH-1:0] B_in,

    output signed [DATA_WIDTH-1:0] A_out,
    output signed [DATA_WIDTH-1:0] B_out,

    output reg signed [ACC_WIDTH-1:0] partial_sum
);

    // Internal pipeline registers
    reg signed [DATA_WIDTH-1:0] A_reg;
    reg signed [DATA_WIDTH-1:0] B_reg;

    // Pass registered data directly to neighbors (1 cycle delay per PE)
    assign A_out = A_reg;
    assign B_out = B_reg;

    always @(posedge clk) begin
        if (rst) begin
            A_reg       <= 0;
            B_reg       <= 0;
            partial_sum <= 0;
        end
        else if (enable) begin
            A_reg       <= A_in;
            B_reg       <= B_in;

            // Multiply-Accumulate using registered inputs
            partial_sum <= partial_sum + (A_reg * B_reg);
        end
    end

endmodule

rtl/systolic_array.v
module systolic_array
#(
    parameter DATA_WIDTH = 8,
    parameter ACC_WIDTH  = 32
)
(
    input clk,
    input rst,
    input enable,

    // Row inputs (A operand enters from the left of each row)
    input signed [DATA_WIDTH-1:0] A0,
    input signed [DATA_WIDTH-1:0] A1,
    input signed [DATA_WIDTH-1:0] A2,
    input signed [DATA_WIDTH-1:0] A3,

    // Column inputs (B operand enters from the top of each column)
    input signed [DATA_WIDTH-1:0] B0,
    input signed [DATA_WIDTH-1:0] B1,
    input signed [DATA_WIDTH-1:0] B2,
    input signed [DATA_WIDTH-1:0] B3,

    // One accumulator output per PE (output-stationary result matrix)
    output wire signed [ACC_WIDTH-1:0] sum00,
    output wire signed [ACC_WIDTH-1:0] sum01,
    output wire signed [ACC_WIDTH-1:0] sum02,
    output wire signed [ACC_WIDTH-1:0] sum03,

    output wire signed [ACC_WIDTH-1:0] sum10,
    output wire signed [ACC_WIDTH-1:0] sum11,
    output wire signed [ACC_WIDTH-1:0] sum12,
    output wire signed [ACC_WIDTH-1:0] sum13,

    output wire signed [ACC_WIDTH-1:0] sum20,
    output wire signed [ACC_WIDTH-1:0] sum21,
    output wire signed [ACC_WIDTH-1:0] sum22,
    output wire signed [ACC_WIDTH-1:0] sum23,

    output wire signed [ACC_WIDTH-1:0] sum30,
    output wire signed [ACC_WIDTH-1:0] sum31,
    output wire signed [ACC_WIDTH-1:0] sum32,
    output wire signed [ACC_WIDTH-1:0] sum33
);

    // -----------------------------------------------------------
    // Internal horizontal wires (A operand, moving left -> right)
    // Naming: A_r_c  = A value leaving row r, column c,
    //                  entering row r, column c+1
    // -----------------------------------------------------------
    wire signed [DATA_WIDTH-1:0] A_0_0, A_0_1, A_0_2;
    wire signed [DATA_WIDTH-1:0] A_1_0, A_1_1, A_1_2;
    wire signed [DATA_WIDTH-1:0] A_2_0, A_2_1, A_2_2;
    wire signed [DATA_WIDTH-1:0] A_3_0, A_3_1, A_3_2;

    // -----------------------------------------------------------
    // Internal vertical wires (B operand, moving top -> bottom)
    // Naming: B_r_c  = B value leaving row r, column c,
    //                  entering row r+1, column c
    // -----------------------------------------------------------
    wire signed [DATA_WIDTH-1:0] B_0_0, B_0_1, B_0_2, B_0_3;
    wire signed [DATA_WIDTH-1:0] B_1_0, B_1_1, B_1_2, B_1_3;
    wire signed [DATA_WIDTH-1:0] B_2_0, B_2_1, B_2_2, B_2_3;

    // =============================================================
    // Row 0
    // =============================================================
    pe #(.DATA_WIDTH(DATA_WIDTH), .ACC_WIDTH(ACC_WIDTH)) u_pe00 (
        .clk(clk), .rst(rst), .enable(enable),
        .A_in(A0),      .B_in(B0),
        .A_out(A_0_0),  .B_out(B_0_0),
        .partial_sum(sum00)
    );

    pe #(.DATA_WIDTH(DATA_WIDTH), .ACC_WIDTH(ACC_WIDTH)) u_pe01 (
        .clk(clk), .rst(rst), .enable(enable),
        .A_in(A_0_0),   .B_in(B1),
        .A_out(A_0_1),  .B_out(B_0_1),
        .partial_sum(sum01)
    );

    pe #(.DATA_WIDTH(DATA_WIDTH), .ACC_WIDTH(ACC_WIDTH)) u_pe02 (
        .clk(clk), .rst(rst), .enable(enable),
        .A_in(A_0_1),   .B_in(B2),
        .A_out(A_0_2),  .B_out(B_0_2),
        .partial_sum(sum02)
    );

    pe #(.DATA_WIDTH(DATA_WIDTH), .ACC_WIDTH(ACC_WIDTH)) u_pe03 (
        .clk(clk), .rst(rst), .enable(enable),
        .A_in(A_0_2),   .B_in(B3),
        .A_out(),       .B_out(B_0_3),   // A_out drives off the right edge, unused
        .partial_sum(sum03)
    );

    // =============================================================
    // Row 1
    // =============================================================
    pe #(.DATA_WIDTH(DATA_WIDTH), .ACC_WIDTH(ACC_WIDTH)) u_pe10 (
        .clk(clk), .rst(rst), .enable(enable),
        .A_in(A1),      .B_in(B_0_0),
        .A_out(A_1_0),  .B_out(B_1_0),
        .partial_sum(sum10)
    );

    pe #(.DATA_WIDTH(DATA_WIDTH), .ACC_WIDTH(ACC_WIDTH)) u_pe11 (
        .clk(clk), .rst(rst), .enable(enable),
        .A_in(A_1_0),   .B_in(B_0_1),
        .A_out(A_1_1),  .B_out(B_1_1),
        .partial_sum(sum11)
    );

    pe #(.DATA_WIDTH(DATA_WIDTH), .ACC_WIDTH(ACC_WIDTH)) u_pe12 (
        .clk(clk), .rst(rst), .enable(enable),
        .A_in(A_1_1),   .B_in(B_0_2),
        .A_out(A_1_2),  .B_out(B_1_2),
        .partial_sum(sum12)
    );

    pe #(.DATA_WIDTH(DATA_WIDTH), .ACC_WIDTH(ACC_WIDTH)) u_pe13 (
        .clk(clk), .rst(rst), .enable(enable),
        .A_in(A_1_2),   .B_in(B_0_3),
        .A_out(),       .B_out(B_1_3),
        .partial_sum(sum13)
    );

    // =============================================================
    // Row 2
    // =============================================================
    pe #(.DATA_WIDTH(DATA_WIDTH), .ACC_WIDTH(ACC_WIDTH)) u_pe20 (
        .clk(clk), .rst(rst), .enable(enable),
        .A_in(A2),      .B_in(B_1_0),
        .A_out(A_2_0),  .B_out(B_2_0),
        .partial_sum(sum20)
    );

    pe #(.DATA_WIDTH(DATA_WIDTH), .ACC_WIDTH(ACC_WIDTH)) u_pe21 (
        .clk(clk), .rst(rst), .enable(enable),
        .A_in(A_2_0),   .B_in(B_1_1),
        .A_out(A_2_1),  .B_out(B_2_1),
        .partial_sum(sum21)
    );

    pe #(.DATA_WIDTH(DATA_WIDTH), .ACC_WIDTH(ACC_WIDTH)) u_pe22 (
        .clk(clk), .rst(rst), .enable(enable),
        .A_in(A_2_1),   .B_in(B_1_2),
        .A_out(A_2_2),  .B_out(B_2_2),
        .partial_sum(sum22)
    );

    pe #(.DATA_WIDTH(DATA_WIDTH), .ACC_WIDTH(ACC_WIDTH)) u_pe23 (
        .clk(clk), .rst(rst), .enable(enable),
        .A_in(A_2_2),   .B_in(B_1_3),
        .A_out(),       .B_out(B_2_3),
        .partial_sum(sum23)
    );

    // =============================================================
    // Row 3
    // =============================================================
    pe #(.DATA_WIDTH(DATA_WIDTH), .ACC_WIDTH(ACC_WIDTH)) u_pe30 (
        .clk(clk), .rst(rst), .enable(enable),
        .A_in(A3),      .B_in(B_2_0),
        .A_out(A_3_0),  .B_out(),        // B_out drives off the bottom edge, unused
        .partial_sum(sum30)
    );

    pe #(.DATA_WIDTH(DATA_WIDTH), .ACC_WIDTH(ACC_WIDTH)) u_pe31 (
        .clk(clk), .rst(rst), .enable(enable),
        .A_in(A_3_0),   .B_in(B_2_1),
        .A_out(A_3_1),  .B_out(),
        .partial_sum(sum31)
    );

    pe #(.DATA_WIDTH(DATA_WIDTH), .ACC_WIDTH(ACC_WIDTH)) u_pe32 (
        .clk(clk), .rst(rst), .enable(enable),
        .A_in(A_3_1),   .B_in(B_2_2),
        .A_out(A_3_2),  .B_out(),
        .partial_sum(sum32)
    );

    pe #(.DATA_WIDTH(DATA_WIDTH), .ACC_WIDTH(ACC_WIDTH)) u_pe33 (
        .clk(clk), .rst(rst), .enable(enable),
        .A_in(A_3_2),   .B_in(B_2_3),
        .A_out(),       .B_out(),
        .partial_sum(sum33)
    );

endmodule

tb/systolic_array_tb.v
`timescale 1ns/1ps

module systolic_array_tb;

    parameter DATA_WIDTH = 8;
    parameter ACC_WIDTH  = 32;

    reg clk;
    reg rst;
    reg enable;

    reg signed [DATA_WIDTH-1:0] A0, A1, A2, A3;
    reg signed [DATA_WIDTH-1:0] B0, B1, B2, B3;

    wire signed [ACC_WIDTH-1:0] sum00, sum01, sum02, sum03;
    wire signed [ACC_WIDTH-1:0] sum10, sum11, sum12, sum13;
    wire signed [ACC_WIDTH-1:0] sum20, sum21, sum22, sum23;
    wire signed [ACC_WIDTH-1:0] sum30, sum31, sum32, sum33;

    //============================================================
    // DUT
    //============================================================

    systolic_array uut (

        .clk(clk),
        .rst(rst),
        .enable(enable),

        .A0(A0),
        .A1(A1),
        .A2(A2),
        .A3(A3),

        .B0(B0),
        .B1(B1),
        .B2(B2),
        .B3(B3),

        .sum00(sum00),
        .sum01(sum01),
        .sum02(sum02),
        .sum03(sum03),

        .sum10(sum10),
        .sum11(sum11),
        .sum12(sum12),
        .sum13(sum13),

        .sum20(sum20),
        .sum21(sum21),
        .sum22(sum22),
        .sum23(sum23),

        .sum30(sum30),
        .sum31(sum31),
        .sum32(sum32),
        .sum33(sum33)
    );

    //============================================================
    // Clock
    //============================================================

    initial
        clk = 0;

    always
        #5 clk = ~clk;

    //============================================================
    // Stimulus
    //============================================================

    initial begin

        $dumpfile("systolic_array_tb.vcd");
        $dumpvars(0, systolic_array_tb);

        rst = 1;
        enable = 0;

        A0 = 0; A1 = 0; A2 = 0; A3 = 0;
        B0 = 0; B1 = 0; B2 = 0; B3 = 0;

        #20;

        rst = 0;
        enable = 1;

        //--------------------------------------------------------
        // Cycle 0
        //--------------------------------------------------------
        @(posedge clk);
        A0<=1;   A1<=0;   A2<=0;   A3<=0;
        B0<=17;  B1<=0;   B2<=0;   B3<=0;

        //--------------------------------------------------------
        // Cycle 1
        //--------------------------------------------------------
        @(posedge clk);
        A0<=2;   A1<=5;   A2<=0;   A3<=0;
        B0<=21;  B1<=18;  B2<=0;   B3<=0;

        //--------------------------------------------------------
        // Cycle 2
        //--------------------------------------------------------
        @(posedge clk);
        A0<=3;   A1<=6;   A2<=9;   A3<=0;
        B0<=25;  B1<=22;  B2<=19;  B3<=0;

        //--------------------------------------------------------
        // Cycle 3
        //--------------------------------------------------------
        @(posedge clk);
        A0<=4;   A1<=7;   A2<=10;  A3<=13;
        B0<=29;  B1<=26;  B2<=23;  B3<=20;

        //--------------------------------------------------------
        // Cycle 4
        //--------------------------------------------------------
        @(posedge clk);
        A0<=0;   A1<=8;   A2<=11;  A3<=14;
        B0<=0;   B1<=30;  B2<=27;  B3<=24;

        //--------------------------------------------------------
        // Cycle 5
        //--------------------------------------------------------
        @(posedge clk);
        A0<=0;   A1<=0;   A2<=12;  A3<=15;
        B0<=0;   B1<=0;   B2<=31;  B3<=28;

        //--------------------------------------------------------
        // Cycle 6
        //--------------------------------------------------------
        @(posedge clk);
        A0<=0;   A1<=0;   A2<=0;   A3<=16;
        B0<=0;   B1<=0;   B2<=0;   B3<=32;

        //--------------------------------------------------------
        // Flush
        //--------------------------------------------------------
        repeat(8)
        begin
            @(posedge clk);
            A0<=0; A1<=0; A2<=0; A3<=0;
            B0<=0; B1<=0; B2<=0; B3<=0;
        end

        #20;

        $display("");
        $display("==============================================");
        $display("Result Matrix");
        $display("==============================================");

        $display("%d %d %d %d",sum00,sum01,sum02,sum03);
        $display("%d %d %d %d",sum10,sum11,sum12,sum13);
        $display("%d %d %d %d",sum20,sum21,sum22,sum23);
        $display("%d %d %d %d",sum30,sum31,sum32,sum33);

        $display("==============================================");

        $finish;

    end

endmodule

systolic_array_tb.vcd
$date
	Wed Jul 29 22:10:49 2026
$end
$version
	Icarus Verilog
$end
$timescale
	1ps
$end
$scope module systolic_array_tb $end
$var wire 32 ! sum33 [31:0] $end
$var wire 32 " sum32 [31:0] $end
$var wire 32 # sum31 [31:0] $end
$var wire 32 $ sum30 [31:0] $end
$var wire 32 % sum23 [31:0] $end
$var wire 32 & sum22 [31:0] $end
$var wire 32 ' sum21 [31:0] $end
$var wire 32 ( sum20 [31:0] $end
$var wire 32 ) sum13 [31:0] $end
$var wire 32 * sum12 [31:0] $end
$var wire 32 + sum11 [31:0] $end
$var wire 32 , sum10 [31:0] $end
$var wire 32 - sum03 [31:0] $end
$var wire 32 . sum02 [31:0] $end
$var wire 32 / sum01 [31:0] $end
$var wire 32 0 sum00 [31:0] $end
$var parameter 32 1 ACC_WIDTH $end
$var parameter 32 2 DATA_WIDTH $end
$var reg 8 3 A0 [7:0] $end
$var reg 8 4 A1 [7:0] $end
$var reg 8 5 A2 [7:0] $end
$var reg 8 6 A3 [7:0] $end
$var reg 8 7 B0 [7:0] $end
$var reg 8 8 B1 [7:0] $end
$var reg 8 9 B2 [7:0] $end
$var reg 8 : B3 [7:0] $end
$var reg 1 ; clk $end
$var reg 1 < enable $end
$var reg 1 = rst $end
$scope module uut $end
$var wire 8 > A0 [7:0] $end
$var wire 8 ? A1 [7:0] $end
$var wire 8 @ A2 [7:0] $end
$var wire 8 A A3 [7:0] $end
$var wire 8 B B0 [7:0] $end
$var wire 8 C B1 [7:0] $end
$var wire 8 D B2 [7:0] $end
$var wire 8 E B3 [7:0] $end
$var wire 1 ; clk $end
$var wire 1 < enable $end
$var wire 1 = rst $end
$var wire 32 F sum33 [31:0] $end
$var wire 32 G sum32 [31:0] $end
$var wire 32 H sum31 [31:0] $end
$var wire 32 I sum30 [31:0] $end
$var wire 32 J sum23 [31:0] $end
$var wire 32 K sum22 [31:0] $end
$var wire 32 L sum21 [31:0] $end
$var wire 32 M sum20 [31:0] $end
$var wire 32 N sum13 [31:0] $end
$var wire 32 O sum12 [31:0] $end
$var wire 32 P sum11 [31:0] $end
$var wire 32 Q sum10 [31:0] $end
$var wire 32 R sum03 [31:0] $end
$var wire 32 S sum02 [31:0] $end
$var wire 32 T sum01 [31:0] $end
$var wire 32 U sum00 [31:0] $end
$var wire 8 V B_2_3 [7:0] $end
$var wire 8 W B_2_2 [7:0] $end
$var wire 8 X B_2_1 [7:0] $end
$var wire 8 Y B_2_0 [7:0] $end
$var wire 8 Z B_1_3 [7:0] $end
$var wire 8 [ B_1_2 [7:0] $end
$var wire 8 \ B_1_1 [7:0] $end
$var wire 8 ] B_1_0 [7:0] $end
$var wire 8 ^ B_0_3 [7:0] $end
$var wire 8 _ B_0_2 [7:0] $end
$var wire 8 ` B_0_1 [7:0] $end
$var wire 8 a B_0_0 [7:0] $end
$var wire 8 b A_3_2 [7:0] $end
$var wire 8 c A_3_1 [7:0] $end
$var wire 8 d A_3_0 [7:0] $end
$var wire 8 e A_2_2 [7:0] $end
$var wire 8 f A_2_1 [7:0] $end
$var wire 8 g A_2_0 [7:0] $end
$var wire 8 h A_1_2 [7:0] $end
$var wire 8 i A_1_1 [7:0] $end
$var wire 8 j A_1_0 [7:0] $end
$var wire 8 k A_0_2 [7:0] $end
$var wire 8 l A_0_1 [7:0] $end
$var wire 8 m A_0_0 [7:0] $end
$var parameter 32 n ACC_WIDTH $end
$var parameter 32 o DATA_WIDTH $end
$scope module u_pe00 $end
$var wire 8 p A_in [7:0] $end
$var wire 8 q B_in [7:0] $end
$var wire 1 ; clk $end
$var wire 1 < enable $end
$var wire 1 = rst $end
$var parameter 32 r ACC_WIDTH $end
$var parameter 32 s DATA_WIDTH $end
$var reg 8 t A_out [7:0] $end
$var reg 8 u A_reg [7:0] $end
$var reg 8 v B_out [7:0] $end
$var reg 8 w B_reg [7:0] $end
$var reg 32 x partial_sum [31:0] $end
$upscope $end
$scope module u_pe01 $end
$var wire 8 y A_in [7:0] $end
$var wire 8 z B_in [7:0] $end
$var wire 1 ; clk $end
$var wire 1 < enable $end
$var wire 1 = rst $end
$var parameter 32 { ACC_WIDTH $end
$var parameter 32 | DATA_WIDTH $end
$var reg 8 } A_out [7:0] $end
$var reg 8 ~ A_reg [7:0] $end
$var reg 8 !" B_out [7:0] $end
$var reg 8 "" B_reg [7:0] $end
$var reg 32 #" partial_sum [31:0] $end
$upscope $end
$scope module u_pe02 $end
$var wire 8 $" A_in [7:0] $end
$var wire 8 %" B_in [7:0] $end
$var wire 1 ; clk $end
$var wire 1 < enable $end
$var wire 1 = rst $end
$var parameter 32 &" ACC_WIDTH $end
$var parameter 32 '" DATA_WIDTH $end
$var reg 8 (" A_out [7:0] $end
$var reg 8 )" A_reg [7:0] $end
$var reg 8 *" B_out [7:0] $end
$var reg 8 +" B_reg [7:0] $end
$var reg 32 ," partial_sum [31:0] $end
$upscope $end
$scope module u_pe03 $end
$var wire 8 -" A_in [7:0] $end
$var wire 8 ." B_in [7:0] $end
$var wire 1 ; clk $end
$var wire 1 < enable $end
$var wire 1 = rst $end
$var parameter 32 /" ACC_WIDTH $end
$var parameter 32 0" DATA_WIDTH $end
$var reg 8 1" A_out [7:0] $end
$var reg 8 2" A_reg [7:0] $end
$var reg 8 3" B_out [7:0] $end
$var reg 8 4" B_reg [7:0] $end
$var reg 32 5" partial_sum [31:0] $end
$upscope $end
$scope module u_pe10 $end
$var wire 8 6" A_in [7:0] $end
$var wire 8 7" B_in [7:0] $end
$var wire 1 ; clk $end
$var wire 1 < enable $end
$var wire 1 = rst $end
$var parameter 32 8" ACC_WIDTH $end
$var parameter 32 9" DATA_WIDTH $end
$var reg 8 :" A_out [7:0] $end
$var reg 8 ;" A_reg [7:0] $end
$var reg 8 <" B_out [7:0] $end
$var reg 8 =" B_reg [7:0] $end
$var reg 32 >" partial_sum [31:0] $end
$upscope $end
$scope module u_pe11 $end
$var wire 8 ?" A_in [7:0] $end
$var wire 8 @" B_in [7:0] $end
$var wire 1 ; clk $end
$var wire 1 < enable $end
$var wire 1 = rst $end
$var parameter 32 A" ACC_WIDTH $end
$var parameter 32 B" DATA_WIDTH $end
$var reg 8 C" A_out [7:0] $end
$var reg 8 D" A_reg [7:0] $end
$var reg 8 E" B_out [7:0] $end
$var reg 8 F" B_reg [7:0] $end
$var reg 32 G" partial_sum [31:0] $end
$upscope $end
$scope module u_pe12 $end
$var wire 8 H" A_in [7:0] $end
$var wire 8 I" B_in [7:0] $end
$var wire 1 ; clk $end
$var wire 1 < enable $end
$var wire 1 = rst $end
$var parameter 32 J" ACC_WIDTH $end
$var parameter 32 K" DATA_WIDTH $end
$var reg 8 L" A_out [7:0] $end
$var reg 8 M" A_reg [7:0] $end
$var reg 8 N" B_out [7:0] $end
$var reg 8 O" B_reg [7:0] $end
$var reg 32 P" partial_sum [31:0] $end
$upscope $end
$scope module u_pe13 $end
$var wire 8 Q" A_in [7:0] $end
$var wire 8 R" B_in [7:0] $end
$var wire 1 ; clk $end
$var wire 1 < enable $end
$var wire 1 = rst $end
$var parameter 32 S" ACC_WIDTH $end
$var parameter 32 T" DATA_WIDTH $end
$var reg 8 U" A_out [7:0] $end
$var reg 8 V" A_reg [7:0] $end
$var reg 8 W" B_out [7:0] $end
$var reg 8 X" B_reg [7:0] $end
$var reg 32 Y" partial_sum [31:0] $end
$upscope $end
$scope module u_pe20 $end
$var wire 8 Z" A_in [7:0] $end
$var wire 8 [" B_in [7:0] $end
$var wire 1 ; clk $end
$var wire 1 < enable $end
$var wire 1 = rst $end
$var parameter 32 \" ACC_WIDTH $end
$var parameter 32 ]" DATA_WIDTH $end
$var reg 8 ^" A_out [7:0] $end
$var reg 8 _" A_reg [7:0] $end
$var reg 8 `" B_out [7:0] $end
$var reg 8 a" B_reg [7:0] $end
$var reg 32 b" partial_sum [31:0] $end
$upscope $end
$scope module u_pe21 $end
$var wire 8 c" A_in [7:0] $end
$var wire 8 d" B_in [7:0] $end
$var wire 1 ; clk $end
$var wire 1 < enable $end
$var wire 1 = rst $end
$var parameter 32 e" ACC_WIDTH $end
$var parameter 32 f" DATA_WIDTH $end
$var reg 8 g" A_out [7:0] $end
$var reg 8 h" A_reg [7:0] $end
$var reg 8 i" B_out [7:0] $end
$var reg 8 j" B_reg [7:0] $end
$var reg 32 k" partial_sum [31:0] $end
$upscope $end
$scope module u_pe22 $end
$var wire 8 l" A_in [7:0] $end
$var wire 8 m" B_in [7:0] $end
$var wire 1 ; clk $end
$var wire 1 < enable $end
$var wire 1 = rst $end
$var parameter 32 n" ACC_WIDTH $end
$var parameter 32 o" DATA_WIDTH $end
$var reg 8 p" A_out [7:0] $end
$var reg 8 q" A_reg [7:0] $end
$var reg 8 r" B_out [7:0] $end
$var reg 8 s" B_reg [7:0] $end
$var reg 32 t" partial_sum [31:0] $end
$upscope $end
$scope module u_pe23 $end
$var wire 8 u" A_in [7:0] $end
$var wire 8 v" B_in [7:0] $end
$var wire 1 ; clk $end
$var wire 1 < enable $end
$var wire 1 = rst $end
$var parameter 32 w" ACC_WIDTH $end
$var parameter 32 x" DATA_WIDTH $end
$var reg 8 y" A_out [7:0] $end
$var reg 8 z" A_reg [7:0] $end
$var reg 8 {" B_out [7:0] $end
$var reg 8 |" B_reg [7:0] $end
$var reg 32 }" partial_sum [31:0] $end
$upscope $end
$scope module u_pe30 $end
$var wire 8 ~" A_in [7:0] $end
$var wire 8 !# B_in [7:0] $end
$var wire 1 ; clk $end
$var wire 1 < enable $end
$var wire 1 = rst $end
$var parameter 32 "# ACC_WIDTH $end
$var parameter 32 ## DATA_WIDTH $end
$var reg 8 $# A_out [7:0] $end
$var reg 8 %# A_reg [7:0] $end
$var reg 8 &# B_out [7:0] $end
$var reg 8 '# B_reg [7:0] $end
$var reg 32 (# partial_sum [31:0] $end
$upscope $end
$scope module u_pe31 $end
$var wire 8 )# A_in [7:0] $end
$var wire 8 *# B_in [7:0] $end
$var wire 1 ; clk $end
$var wire 1 < enable $end
$var wire 1 = rst $end
$var parameter 32 +# ACC_WIDTH $end
$var parameter 32 ,# DATA_WIDTH $end
$var reg 8 -# A_out [7:0] $end
$var reg 8 .# A_reg [7:0] $end
$var reg 8 /# B_out [7:0] $end
$var reg 8 0# B_reg [7:0] $end
$var reg 32 1# partial_sum [31:0] $end
$upscope $end
$scope module u_pe32 $end
$var wire 8 2# A_in [7:0] $end
$var wire 8 3# B_in [7:0] $end
$var wire 1 ; clk $end
$var wire 1 < enable $end
$var wire 1 = rst $end
$var parameter 32 4# ACC_WIDTH $end
$var parameter 32 5# DATA_WIDTH $end
$var reg 8 6# A_out [7:0] $end
$var reg 8 7# A_reg [7:0] $end
$var reg 8 8# B_out [7:0] $end
$var reg 8 9# B_reg [7:0] $end
$var reg 32 :# partial_sum [31:0] $end
$upscope $end
$scope module u_pe33 $end
$var wire 8 ;# A_in [7:0] $end
$var wire 8 <# B_in [7:0] $end
$var wire 1 ; clk $end
$var wire 1 < enable $end
$var wire 1 = rst $end
$var parameter 32 =# ACC_WIDTH $end
$var parameter 32 ># DATA_WIDTH $end
$var reg 8 ?# A_out [7:0] $end
$var reg 8 @# A_reg [7:0] $end
$var reg 8 A# B_out [7:0] $end
$var reg 8 B# B_reg [7:0] $end
$var reg 32 C# partial_sum [31:0] $end
$upscope $end
$upscope $end
$upscope $end
$enddefinitions $end
$comment Show the parameter values. $end
$dumpall
b1000 >#
b100000 =#
b1000 5#
b100000 4#
b1000 ,#
b100000 +#
b1000 ##
b100000 "#
b1000 x"
b100000 w"
b1000 o"
b100000 n"
b1000 f"
b100000 e"
b1000 ]"
b100000 \"
b1000 T"
b100000 S"
b1000 K"
b100000 J"
b1000 B"
b100000 A"
b1000 9"
b100000 8"
b1000 0"
b100000 /"
b1000 '"
b100000 &"
b1000 |
b100000 {
b1000 s
b100000 r
b1000 o
b100000 n
b1000 2
b100000 1
$end
#0
$dumpvars
bx C#
bx B#
bx A#
bx @#
bx ?#
bx <#
bx ;#
bx :#
bx 9#
bx 8#
bx 7#
bx 6#
bx 3#
bx 2#
bx 1#
bx 0#
bx /#
bx .#
bx -#
bx *#
bx )#
bx (#
bx '#
bx &#
bx %#
bx $#
bx !#
b0 ~"
bx }"
bx |"
bx {"
bx z"
bx y"
bx v"
bx u"
bx t"
bx s"
bx r"
bx q"
bx p"
bx m"
bx l"
bx k"
bx j"
bx i"
bx h"
bx g"
bx d"
bx c"
bx b"
bx a"
bx `"
bx _"
bx ^"
bx ["
b0 Z"
bx Y"
bx X"
bx W"
bx V"
bx U"
bx R"
bx Q"
bx P"
bx O"
bx N"
bx M"
bx L"
bx I"
bx H"
bx G"
bx F"
bx E"
bx D"
bx C"
bx @"
bx ?"
bx >"
bx ="
bx <"
bx ;"
bx :"
bx 7"
b0 6"
bx 5"
bx 4"
bx 3"
bx 2"
bx 1"
b0 ."
bx -"
bx ,"
bx +"
bx *"
bx )"
bx ("
b0 %"
bx $"
bx #"
bx ""
bx !"
bx ~
bx }
b0 z
bx y
bx x
bx w
bx v
bx u
bx t
b0 q
b0 p
bx m
bx l
bx k
bx j
bx i
bx h
bx g
bx f
bx e
bx d
bx c
bx b
bx a
bx `
bx _
bx ^
bx ]
bx \
bx [
bx Z
bx Y
bx X
bx W
bx V
bx U
bx T
bx S
bx R
bx Q
bx P
bx O
bx N
bx M
bx L
bx K
bx J
bx I
bx H
bx G
bx F
b0 E
b0 D
b0 C
b0 B
b0 A
b0 @
b0 ?
b0 >
1=
0<
0;
b0 :
b0 9
b0 8
b0 7
b0 6
b0 5
b0 4
b0 3
bx 0
bx /
bx .
bx -
bx ,
bx +
bx *
bx )
bx (
bx '
bx &
bx %
bx $
bx #
bx "
bx !
$end
#5000
b0 0
b0 U
b0 x
b0 a
b0 v
b0 7"
b0 m
b0 t
b0 y
b0 w
b0 u
b0 /
b0 T
b0 #"
b0 `
b0 !"
b0 @"
b0 l
b0 }
b0 $"
b0 ""
b0 ~
b0 .
b0 S
b0 ,"
b0 _
b0 *"
b0 I"
b0 k
b0 ("
b0 -"
b0 +"
b0 )"
b0 -
b0 R
b0 5"
b0 ^
b0 3"
b0 R"
b0 1"
b0 4"
b0 2"
b0 ,
b0 Q
b0 >"
b0 ]
b0 <"
b0 ["
b0 j
b0 :"
b0 ?"
b0 ="
b0 ;"
b0 +
b0 P
b0 G"
b0 \
b0 E"
b0 d"
b0 i
b0 C"
b0 H"
b0 F"
b0 D"
b0 *
b0 O
b0 P"
b0 [
b0 N"
b0 m"
b0 h
b0 L"
b0 Q"
b0 O"
b0 M"
b0 )
b0 N
b0 Y"
b0 Z
b0 W"
b0 v"
b0 U"
b0 X"
b0 V"
b0 (
b0 M
b0 b"
b0 Y
b0 `"
b0 !#
b0 g
b0 ^"
b0 c"
b0 a"
b0 _"
b0 '
b0 L
b0 k"
b0 X
b0 i"
b0 *#
b0 f
b0 g"
b0 l"
b0 j"
b0 h"
b0 &
b0 K
b0 t"
b0 W
b0 r"
b0 3#
b0 e
b0 p"
b0 u"
b0 s"
b0 q"
b0 %
b0 J
b0 }"
b0 V
b0 {"
b0 <#
b0 y"
b0 |"
b0 z"
b0 $
b0 I
b0 (#
b0 &#
b0 d
b0 $#
b0 )#
b0 '#
b0 %#
b0 #
b0 H
b0 1#
b0 /#
b0 c
b0 -#
b0 2#
b0 0#
b0 .#
b0 "
b0 G
b0 :#
b0 8#
b0 b
b0 6#
b0 ;#
b0 9#
b0 7#
b0 !
b0 F
b0 C#
b0 A#
b0 ?#
b0 B#
b0 @#
1;
#10000
0;
#15000
1;
#20000
0;
1<
0=
#25000
b10001 7
b10001 B
b10001 q
b1 3
b1 >
b1 p
1;
#30000
0;
#35000
b10010 8
b10010 C
b10010 z
b10101 7
b10101 B
b10101 q
b101 4
b101 ?
b101 6"
b10 3
b10 >
b10 p
b10001 w
b1 u
1;
#40000
0;
#45000
b10001 0
b10001 U
b10001 x
b10001 a
b10001 v
b10001 7"
b1 m
b1 t
b1 y
b10101 w
b10 u
b10010 ""
b101 ;"
b10011 9
b10011 D
b10011 %"
b10110 8
b10110 C
b10110 z
b11001 7
b11001 B
b11001 q
b1001 5
b1001 @
b1001 Z"
b110 4
b110 ?
b110 6"
b11 3
b11 >
b11 p
1;
#50000
0;
#55000
b10100 :
b10100 E
b10100 ."
b10111 9
b10111 D
b10111 %"
b11010 8
b11010 C
b11010 z
b11101 7
b11101 B
b11101 q
b1101 6
b1101 A
b1101 ~"
b1010 5
b1010 @
b1010 Z"
b111 4
b111 ?
b111 6"
b100 3
b100 >
b100 p
b1001 _"
b101 j
b101 :"
b101 ?"
b10001 ="
b110 ;"
b10011 +"
b10010 `
b10010 !"
b10010 @"
b10110 ""
b1 ~
b111011 0
b111011 U
b111011 x
b10101 a
b10101 v
b10101 7"
b10 m
b10 t
b10 y
b11001 w
b11 u
1;
#60000
0;
#65000
b10000110 0
b10000110 U
b10000110 x
b11001 a
b11001 v
b11001 7"
b11 m
b11 t
b11 y
b11101 w
b100 u
b10110 /
b10110 T
b10110 #"
b10110 `
b10110 !"
b10110 @"
b1 l
b1 }
b1 $"
b11010 ""
b10 ~
b10011 _
b10011 *"
b10011 I"
b10111 +"
b10100 4"
b1100110 ,
b1100110 Q
b1100110 >"
b10001 ]
b10001 <"
b10001 ["
b110 j
b110 :"
b110 ?"
b10101 ="
b111 ;"
b10010 F"
b101 D"
b1001 g
b1001 ^"
b1001 c"
b1010 _"
b1101 %#
b11000 :
b11000 E
b11000 ."
b11011 9
b11011 D
b11011 %"
b11110 8
b11110 C
b11110 z
b0 7
b0 B
b0 q
b1110 6
b1110 A
b1110 ~"
b1011 5
b1011 @
b1011 Z"
b1000 4
b1000 ?
b1000 6"
b0 3
b0 >
b0 p
1;
#70000
0;
